LICENSE
MANIFEST.in
README.rst
setup.py
django_standbydb_router.egg-info/PKG-INFO
django_standbydb_router.egg-info/SOURCES.txt
django_standbydb_router.egg-info/dependency_links.txt
django_standbydb_router.egg-info/not-zip-safe
django_standbydb_router.egg-info/top_level.txt
standbydb/__init__.py
standbydb/tests.py