Metadata-Version: 1.1
Name: django-standbydb-router
Version: 0.2
Summary: Round-robin standbydb router for Django.
Home-page: https://github.com/devopscenter/django-standby-router
Author: Jeff Balogh and Josh
Author-email: josh@devops.center
License: BSD
Platform: UNKNOWN
Classifier: Development Status :: 4 - Beta
Classifier: Environment :: Web Environment
Classifier: Environment :: Web Environment :: Mozilla
Classifier: Framework :: Django
Classifier: Intended Audience :: Developers
Classifier: License :: OSI Approved :: BSD License
Classifier: Operating System :: OS Independent
Classifier: Programming Language :: Python
Classifier: Topic :: Software Development :: Libraries :: Python Modules
